{
  "lust": [
    {
      "url": "https://open.spotify.com/track/2Oycxb8QbPkpHTo8ZrmG0B?si=23a49b273840449b",
      "title": "prisoner"
    },
    {
      "url": "https://open.spotify.com/track/6usohdchdzW9oML7VC4Uhk?si=e1911f7c19d74ab5",
      "title": "lose control"
    },
    {
      "url": "https://open.spotify.com/track/43oK4OAWUsRZUDVeHtKI4U?si=976c3313e268444f",
      "title": "new rules"
    },
    {
      "url": "https://open.spotify.com/track/6I9VzXrHxO9rA9A5euc8Ak?si=6e0fa21de96545aa",
      "title": "toxic"
    },
    {
      "url": "https://open.spotify.com/track/0k4d5YPDr1r7FX77VdqWez?si=11788cc87cf54bcb",
      "title": "you right"
    },
    {
      "url": "https://open.spotify.com/track/6y0Etr2KJr0sdcEp7ajoUK?si=e2eb826359a24ab4",
      "title": "cosmic girl"
    },
    {
      "url": "https://open.spotify.com/track/3E7ZwUMJFqpsDOJzEkBrQ7?si=9315745582fa4064",
      "title": "can't get you out of my head"
    },
    {
      "url": "https://open.spotify.com/track/4bSXYm8H83RaJyTdiXWlbb?si=179a8884a2ef4f5f",
      "title": "waiting"
    },
    {
      "url": "https://open.spotify.com/track/3zidJjXGWgKqgQnfb6hKak?si=73bd87924fbd48ce",
      "title": "losing my way"
    },
    {
      "url": "https://open.spotify.com/track/1B5fbRxnB26duk77yCBWvS?si=5cf26d702804481b",
      "title": "go back home"
    }
  ],
  "midnightClarity": [
    {
      "url": "#",
      "title": "song 1"
    },
    {
      "url": "#",
      "title": "song 2"
    },
    {
      "url": "#",
      "title": "song 3"
    },
    {
      "url": "#",
      "title": "song 4"
    },
    {
      "url": "#",
      "title": "song 5"
    },
    {
      "url": "#",
      "title": "song 6"
    },
    {
      "url": "#",
      "title": "song 7"
    },
    {
      "url": "#",
      "title": "song 8"
    },
    {
      "url": "#",
      "title": "song 9"
    },
    {
      "url": "#",
      "title": "song 10"
    }
  ]
}
